print_env/__init__.py
print_env/cli.py
print_env/exts.py
print_env/loader.py
print_env/utils.py
print_env/version.py
tests/unit/__init__.py
tests/unit/test_exts.py
tests/unit/test_loader.py
print_env-2.3.0.dist-info/LICENSE
print_env-2.3.0.dist-info/METADATA
print_env-2.3.0.dist-info/WHEEL
print_env-2.3.0.dist-info/entry_points.txt
print_env-2.3.0.dist-info/top_level.txt
print_env-2.3.0.dist-info/RECORD
