Metadata-Version: 2.1
Name: print-env
Version: 2.3.0
Summary: CLI to print environment variables from supported sources.
Home-page: https://github.com/woozyking/print-env
Author: Runzhou Li (Leo)
Author-email: me@runzhou.li
License: MIT
Classifier: License :: OSI Approved :: MIT License
Classifier: Programming Language :: Python
Classifier: Programming Language :: Python :: 3
Classifier: Programming Language :: Python :: 3.6
Classifier: Programming Language :: Python :: 3.7
Classifier: Programming Language :: Python :: 3.8
Classifier: Programming Language :: Python :: 3.9
Classifier: Programming Language :: Python :: Implementation :: CPython
Classifier: Programming Language :: Python :: Implementation :: PyPy
Requires-Python: >=3.6
License-File: LICENSE
